sqltemplate/__init__.py
sqltemplate/clause.py
sqltemplate/query.py
sqltemplate/sqlcore.py
pysqltemplate-0.0.1.0.dist-info/LICENSE.txt
pysqltemplate-0.0.1.0.dist-info/METADATA
pysqltemplate-0.0.1.0.dist-info/WHEEL
pysqltemplate-0.0.1.0.dist-info/top_level.txt
pysqltemplate-0.0.1.0.dist-info/RECORD
