Metadata-Version: 2.1
Name: pysqltemplate
Version: 0.0.1.0
Summary: A package to write composable, generic SQL objects that can be flexibly reused and combined. Like an ORM, but not an ORM.
Home-page: https://gitlab.com/krcrouse/sqltemplate
Author: Kevin Crouse
Author-email: krcrouse@gmail.com
License: UNKNOWN
Platform: UNKNOWN
Classifier: Programming Language :: Python :: 3.7
Classifier: License :: OSI Approved :: Apache Software License
Classifier: Operating System :: OS Independent
Classifier: Development Status :: 3 - Alpha
